<?xml version='1.0' encoding='UTF-8' standalone='yes'?>
<tomtom version="5.1.0" release="Fri Oct 11 15:53:28 2019 -0700">
  <model>
    <command_line>tomtom -no-ssc -thresh 0.01 -o result/x00988/x00988.out result/x00988/x00988.meme ../../../JASPAR2020.txt</command_line>
    <distance_measure value="ed"/>
    <threshold type="qvalue">0.01</threshold>
    <alphabet name="DNA" like="dna">
      <letter id="A" symbol="A" complement="T" name="Adenine" colour="CC0000"/>
      <letter id="C" symbol="C" complement="G" name="Cytosine" colour="0000CC"/>
      <letter id="G" symbol="G" complement="C" name="Guanine" colour="FFB300"/>
      <letter id="T" symbol="T" aliases="U" complement="A" name="Thymine" colour="008000"/>
      <letter id="N" symbol="N" aliases="X." equals="ACGT" name="Any base"/>
      <letter id="V" symbol="V" equals="ACG" name="Not T"/>
      <letter id="H" symbol="H" equals="ACT" name="Not G"/>
      <letter id="D" symbol="D" equals="AGT" name="Not C"/>
      <letter id="B" symbol="B" equals="CGT" name="Not A"/>
      <letter id="M" symbol="M" equals="AC" name="Amino"/>
      <letter id="R" symbol="R" equals="AG" name="Purine"/>
      <letter id="W" symbol="W" equals="AT" name="Weak"/>
      <letter id="S" symbol="S" equals="CG" name="Strong"/>
      <letter id="Y" symbol="Y" equals="CT" name="Pyrimidine"/>
      <letter id="K" symbol="K" equals="GT" name="Keto"/>
    </alphabet>
    <strands>both</strands>
    <background from="--query--" A="0.25" C="0.25" G="0.25" T="0.25"/>
    <host>n05</host>
    <when>Mon Nov 30 03:36:02 2020</when>
  </model>
  <query_dbs>
    <db source="result/x00988/x00988.meme" name="x00988" loaded="1" excluded="0" last_mod_date="Mon Nov 30 03:36:02 2020"/>
  </query_dbs>
  <target_dbs>
    <db source="../../../JASPAR2020.txt" name="JASPAR2020.txt" loaded="1011" excluded="0" last_mod_date="Fri Oct  9 07:50:57 2020"/>
  </target_dbs>
  <queries>
    <motif db="0" id="1116_6003_0.7697_0.3846" length="163" nsites="998">
      <pos A="0.492453" C="0.16049" G="0.189575" T="0.157481"/>
      <pos A="0.205415" C="0.350691" G="0.3557" T="0.0881922"/>
      <pos A="0.571683" C="0.167511" G="0.146449" T="0.114357"/>
      <pos A="0.341674" C="0.18137" G="0.16033" T="0.316626"/>
      <pos A="0.158326" C="0.112238" G="0.4078" T="0.321636"/>
      <pos A="0.257514" C="0.353697" G="0.183374" T="0.205415"/>
      <pos A="0.180368" C="0.334661" G="0.398783" T="0.0861884"/>
      <pos A="0.375739" C="0.182372" G="0.254509" T="0.187381"/>
      <pos A="0.141152" C="0.257256" G="0.184191" T="0.4174"/>
      <pos A="0.279837" C="0.15347" G="0.431276" T="0.135417"/>
      <pos A="0.345681" C="0.294585" G="0.261522" T="0.0982112"/>
      <pos A="0.249499" C="0.438859" G="0.228459" T="0.0831827"/>
      <pos A="0.295586" C="0.118249" G="0.272543" T="0.313621"/>
      <pos A="0.154164" C="0.132144" G="0.432414" T="0.281278"/>
      <pos A="0.237476" C="0.13929" G="0.295586" T="0.327647"/>
      <pos A="0.16033" C="0.258516" G="0.231465" T="0.349689"/>
      <pos A="0.428267" C="0.193587" G="0.294881" T="0.0832667"/>
      <pos A="0.163336" C="0.291579" G="0.315624" T="0.229461"/>
      <pos A="0.179186" C="0.180187" G="0.462441" T="0.178185"/>
      <pos A="0.290577" C="0.180368" G="0.237476" T="0.291579"/>
      <pos A="0.400787" C="0.251503" G="0.253507" T="0.0942036"/>
      <pos A="0.314308" C="0.258257" G="0.142153" T="0.285281"/>
      <pos A="0.382133" C="0.324967" G="0.221668" T="0.0712319"/>
      <pos A="0.203616" C="0.193587" G="0.277831" T="0.324967"/>
      <pos A="0.0751675" C="0.350691" G="0.300596" T="0.273545"/>
      <pos A="0.420403" C="0.13915" G="0.29429" T="0.146156"/>
      <pos A="0.227457" C="0.389766" G="0.192391" T="0.190387"/>
      <pos A="0.340331" C="0.305299" G="0.235236" T="0.119132"/>
      <pos A="0.261522" C="0.206417" G="0.259518" T="0.272543"/>
      <pos A="0.15016" C="0.138149" G="0.619583" T="0.0921078"/>
      <pos A="0.0762464" C="0.256769" G="0.425258" T="0.241726"/>
      <pos A="0.164338" C="0.177362" G="0.393774" T="0.264528"/>
      <pos A="0.145301" C="0.0681542" G="0.342676" T="0.443869"/>
      <pos A="0.0922928" C="0.181552" G="0.451334" T="0.274822"/>
      <pos A="0.288573" C="0.282562" G="0.295586" T="0.133279"/>
      <pos A="0.262524" C="0.333659" G="0.264528" T="0.13929"/>
      <pos A="0.307609" C="0.205415" G="0.121255" T="0.365719"/>
      <pos A="0.357704" C="0.183374" G="0.203412" T="0.25551"/>
      <pos A="0.286569" C="0.17636" G="0.250501" T="0.286569"/>
      <pos A="0.149309" C="0.395777" G="0.184376" T="0.270539"/>
      <pos A="0.213431" C="0.213431" G="0.397781" T="0.175358"/>
      <pos A="0.1942" C="0.135147" G="0.413397" T="0.257256"/>
      <pos A="0.155165" C="0.202207" G="0.389375" T="0.253253"/>
      <pos A="0.177362" C="0.180368" G="0.346683" T="0.295586"/>
      <pos A="0.248497" C="0.256512" G="0.209423" T="0.285567"/>
      <pos A="0.375739" C="0.327647" G="0.186379" T="0.110234"/>
      <pos A="0.381368" C="0.334326" G="0.147157" T="0.137148"/>
      <pos A="0.251755" C="0.233703" G="0.176537" T="0.338005"/>
      <pos A="0.184376" C="0.0741656" G="0.319632" T="0.421827"/>
      <pos A="0.0652145" C="0.141435" G="0.464372" T="0.328979"/>
      <pos A="0.238478" C="0.295586" G="0.216436" T="0.249499"/>
      <pos A="0.305605" C="0.28156" G="0.253507" T="0.159328"/>
      <pos A="0.334661" C="0.262524" G="0.200406" T="0.20241"/>
      <pos A="0.29759" C="0.372733" G="0.0791751" T="0.250501"/>
      <pos A="0.123259" C="0.39177" G="0.1443" T="0.340672"/>
      <pos A="0.393774" C="0.040101" G="0.351693" T="0.214433"/>
      <pos A="0.205415" C="0.338668" G="0.242486" T="0.213431"/>
      <pos A="0.156322" C="0.340672" G="0.248497" T="0.254509"/>
      <pos A="0.35034" C="0.244245" G="0.289285" T="0.116129"/>
      <pos A="0.346683" C="0.403793" G="0.0661504" T="0.183374"/>
      <pos A="0.27655" C="0.29759" G="0.146303" T="0.279556"/>
      <pos A="0.348687" C="0.141294" G="0.234471" T="0.275548"/>
      <pos A="0.159328" C="0.345681" G="0.273545" T="0.221446"/>
      <pos A="0.523544" C="0.135417" G="0.245737" T="0.0953015"/>
      <pos A="0.207419" C="0.270539" G="0.119251" T="0.402791"/>
      <pos A="0.286569" C="0.25551" G="0.333659" T="0.124261"/>
      <pos A="0.304604" C="0.280558" G="0.153317" T="0.261522"/>
      <pos A="0.353343" C="0.185191" G="0.33933" T="0.122135"/>
      <pos A="0.20241" C="0.20241" G="0.251503" T="0.343678"/>
      <pos A="0.133279" C="0.250501" G="0.480939" T="0.135282"/>
      <pos A="0.377743" C="0.304604" G="0.112238" T="0.205415"/>
      <pos A="0.152315" C="0.379747" G="0.214433" T="0.253507"/>
      <pos A="0.542599" C="0.181552" G="0.231697" T="0.0441526"/>
      <pos A="0.21844" C="0.289575" G="0.0871903" T="0.404794"/>
      <pos A="0.261522" C="0.274547" G="0.368725" T="0.0952055"/>
      <pos A="0.253507" C="0.216436" G="0.298592" T="0.231465"/>
      <pos A="0.0790961" C="0.358347" G="0.464443" T="0.0981132"/>
      <pos A="0.488954" C="0.228459" G="0.17636" T="0.106226"/>
      <pos A="0.138426" C="0.416232" G="0.162496" T="0.282846"/>
      <pos A="0.469918" C="0.122257" G="0.317628" T="0.090196"/>
      <pos A="0.370729" C="0.128269" G="0.111236" T="0.389766"/>
      <pos A="0.361712" C="0.303602" G="0.156322" T="0.178364"/>
      <pos A="0.242486" C="0.236474" G="0.490958" T="0.030082"/>
      <pos A="0.220223" C="0.436417" G="0.11713" T="0.226228"/>
      <pos A="0.182372" C="0.442867" G="0.243488" T="0.131275"/>
      <pos A="0.582131" C="0.080177" G="0.157324" T="0.180368"/>
      <pos A="0.111236" C="0.312619" G="0.168345" T="0.4078"/>
      <pos A="0.430412" C="0.107121" G="0.436417" T="0.0260484"/>
      <pos A="0.291872" C="0.145446" G="0.21565" T="0.347031"/>
      <pos A="0.124261" C="0.437857" G="0.370729" T="0.0671523"/>
      <pos A="0.449429" C="0.169177" G="0.115129" T="0.266264"/>
      <pos A="0.179366" C="0.311617" G="0.21844" T="0.290577"/>
      <pos A="0.372104" C="0.109342" G="0.378121" T="0.140432"/>
      <pos A="0.040141" C="0.529561" G="0.255766" T="0.174532"/>
      <pos A="0.513" C="0.182372" G="0.275548" T="0.0290801"/>
      <pos A="0.0911069" C="0.303298" G="0.0330547" T="0.572541"/>
      <pos A="0.331655" C="0.122257" G="0.531034" T="0.0150535"/>
      <pos A="0.307609" C="0.212429" G="0.0541276" T="0.425834"/>
      <pos A="0.0671523" C="0.527026" G="0.351693" T="0.0541276"/>
      <pos A="0.738166" C="0.113354" G="0.0511729" T="0.0973073"/>
      <pos A="0.0670853" C="0.488464" G="0.0961114" T="0.348338"/>
      <pos A="0.423831" C="0.157324" G="0.338668" T="0.080177"/>
      <pos A="0.142296" C="0.213431" G="0.24449" T="0.399785"/>
      <pos A="0.146303" C="0.285567" G="0.513" T="0.0551295"/>
      <pos A="0.515003" C="0.0731637" G="0.159328" T="0.252505"/>
      <pos A="0.0580772" C="0.453433" G="0.178185" T="0.310304"/>
      <pos A="0.553076" C="0.115244" G="0.310615" T="0.0210649"/>
      <pos A="0.177362" C="0.301598" G="0.177362" T="0.343678"/>
      <pos A="0.203412" C="0.390768" G="0.321636" T="0.0841846"/>
      <pos A="0.169347" C="0.101217" G="0.156322" T="0.573114"/>
      <pos A="0.226455" C="0.34468" G="0.384756" T="0.0441086"/>
      <pos A="0.624211" C="0.1974" G="0.0370953" T="0.141294"/>
      <pos A="0.194395" C="0.306607" G="0.252505" T="0.246493"/>
      <pos A="0.430844" C="0.221446" G="0.231465" T="0.116245"/>
      <pos A="0.0531257" C="0.366721" G="0.116245" T="0.463907"/>
      <pos A="0.361072" C="0.249749" G="0.340011" T="0.0491671"/>
      <pos A="0.164502" C="0.31193" G="0.0230917" T="0.500477"/>
      <pos A="0.310615" C="0.325643" G="0.317628" T="0.0461124"/>
      <pos A="0.450331" C="0.220665" G="0.0712319" T="0.257772"/>
      <pos A="0.040101" C="0.538047" G="0.288573" T="0.133279"/>
      <pos A="0.532036" C="0.169347" G="0.234471" T="0.0641466"/>
      <pos A="0.205621" C="0.245737" G="0.107336" T="0.441305"/>
      <pos A="0.22345" C="0.152315" G="0.410806" T="0.213431"/>
      <pos A="0.237476" C="0.179366" G="0.361712" T="0.221446"/>
      <pos A="0.285854" C="0.163499" G="0.250752" T="0.299895"/>
      <pos A="0.322638" C="0.166341" G="0.236474" T="0.274547"/>
      <pos A="0.116245" C="0.34468" G="0.458897" T="0.080177"/>
      <pos A="0.492468" C="0.0740916" G="0.0891051" T="0.344335"/>
      <pos A="0.0761694" C="0.410806" G="0.296588" T="0.216436"/>
      <pos A="0.423831" C="0.252505" G="0.278554" T="0.0451105"/>
      <pos A="0.275824" C="0.256769" G="0.290869" T="0.176537"/>
      <pos A="0.253507" C="0.0851865" G="0.401789" T="0.259518"/>
      <pos A="0.0982112" C="0.0481162" G="0.335662" T="0.518009"/>
      <pos A="0.0671523" C="0.270539" G="0.57111" T="0.0911979"/>
      <pos A="0.241242" C="0.279276" G="0.211215" T="0.268266"/>
      <pos A="0.285567" C="0.312619" G="0.316626" T="0.0851865"/>
      <pos A="0.372733" C="0.0781732" G="0.165339" T="0.383755"/>
      <pos A="0.0841846" C="0.261522" G="0.41281" T="0.241484"/>
      <pos A="0.350691" C="0.0741656" G="0.475929" T="0.0992131"/>
      <pos A="0.122257" C="0.38676" G="0.161332" T="0.329651"/>
      <pos A="0.359708" C="0.219442" G="0.363716" T="0.0571333"/>
      <pos A="0.246493" C="0.0881922" G="0.129271" T="0.536043"/>
      <pos A="0.0881922" C="0.249499" G="0.492962" T="0.169347"/>
      <pos A="0.340672" C="0.0390991" G="0.442867" T="0.177362"/>
      <pos A="0.173355" C="0.463907" G="0.154319" T="0.208421"/>
      <pos A="0.303602" C="0.179366" G="0.231465" T="0.285567"/>
      <pos A="0.186379" C="0.187381" G="0.335662" T="0.290577"/>
      <pos A="0.3557" C="0.204414" G="0.211427" T="0.228459"/>
      <pos A="0.11324" C="0.225453" G="0.417819" T="0.243488"/>
      <pos A="0.184376" C="0.351693" G="0.266531" T="0.1974"/>
      <pos A="0.211427" C="0.401789" G="0.171351" T="0.215434"/>
      <pos A="0.399183" C="0.224677" G="0.217656" T="0.158484"/>
      <pos A="0.184191" C="0.263262" G="0.169177" T="0.38337"/>
      <pos A="0.169517" C="0.306915" G="0.414227" T="0.109342"/>
      <pos A="0.243732" C="0.369095" G="0.139429" T="0.247743"/>
      <pos A="0.243488" C="0.286569" G="0.330653" T="0.13929"/>
      <pos A="0.270539" C="0.243488" G="0.322638" T="0.163336"/>
      <pos A="0.178185" C="0.452432" G="0.202207" T="0.167175"/>
      <pos A="0.26379" C="0.296886" G="0.235708" T="0.203616"/>
      <pos A="0.229691" C="0.307918" G="0.266798" T="0.195592"/>
      <pos A="0.375362" C="0.192198" G="0.282279" T="0.15016"/>
      <pos A="0.261784" C="0.230694" G="0.196595" T="0.310927"/>
      <pos A="0.229461" C="0.161332" G="0.469918" T="0.13929"/>
    </motif>
  </queries>
  <targets>
    <motif db="0" id="MA0068.1" alt="Pax4" length="30" nsites="21"
        url="http://jaspar.genereg.net/matrix/MA0068.1">
      <pos A="0.332938" C="0.0959715" G="0.522512" T="0.0485782"/>
      <pos A="0.949052" C="0.00118483" G="0.0485782" T="0.00118483"/>
      <pos A="0.759479" C="0.0959715" G="0.0485782" T="0.0959715"/>
      <pos A="0.522512" C="0.0485782" G="0.0485782" T="0.380331"/>
      <pos A="0.617299" C="0.0485782" G="0.143365" T="0.190758"/>
      <pos A="0.522512" C="0.143365" G="0.0485782" T="0.285545"/>
      <pos A="0.285545" C="0.0485782" G="0.0959715" T="0.569906"/>
      <pos A="0.427725" C="0.0485782" G="0.0485782" T="0.475118"/>
      <pos A="0.238151" C="0.143365" G="0.285545" T="0.332938"/>
      <pos A="0.238151" C="0.522512" G="0.0485782" T="0.190758"/>
      <pos A="0.285545" C="0.522512" G="0.190758" T="0.00118483"/>
      <pos A="0.332938" C="0.332938" G="0.238151" T="0.0959715"/>
      <pos A="0.380331" C="0.332938" G="0.0959715" T="0.190758"/>
      <pos A="0.285545" C="0.238151" G="0.0485782" T="0.427725"/>
      <pos A="0.475118" C="0.238151" G="0.190758" T="0.0959715"/>
      <pos A="0.190758" C="0.380331" G="0.190758" T="0.238151"/>
      <pos A="0.143365" C="0.285545" G="0.190758" T="0.380331"/>
      <pos A="0.332938" C="0.380331" G="0.143365" T="0.143365"/>
      <pos A="0.190758" C="0.427725" G="0.143365" T="0.238151"/>
      <pos A="0.427725" C="0.285545" G="0.0959715" T="0.190758"/>
      <pos A="0.238151" C="0.332938" G="0.238151" T="0.190758"/>
      <pos A="0.238151" C="0.285545" G="0.0959715" T="0.380331"/>
      <pos A="0.332938" C="0.522512" G="0.00118483" T="0.143365"/>
      <pos A="0.285545" C="0.427725" G="0.0485782" T="0.238151"/>
      <pos A="0.143365" C="0.569906" G="0.0959715" T="0.190758"/>
      <pos A="0.332938" C="0.427725" G="0.0959715" T="0.143365"/>
      <pos A="0.143365" C="0.569906" G="0.0959715" T="0.190758"/>
      <pos A="0.0485782" C="0.522512" G="0.143365" T="0.285545"/>
      <pos A="0.285545" C="0.522512" G="0.0485782" T="0.143365"/>
      <pos A="0.143365" C="0.617299" G="0.0959715" T="0.143365"/>
    </motif>
  </targets>
  <matches>
    <query idx="0">
      <target idx="0" rc="y" off="-29" pv="8.82e-10" ev="8.92e-07" qv="1.78e-06"/>
    </query>
  </matches>
  <runtime cycles="1939574867" seconds="1939.575"/>
</tomtom>
