<?xml version='1.0' encoding='UTF-8' standalone='yes'?>
<tomtom version="5.1.0" release="Fri Oct 11 15:53:28 2019 -0700">
  <model>
    <command_line>tomtom -no-ssc -thresh 0.01 -o result/x13154/x13154.out result/x13154/x13154.meme ../../../JASPAR2020.txt</command_line>
    <distance_measure value="ed"/>
    <threshold type="qvalue">0.01</threshold>
    <alphabet name="DNA" like="dna">
      <letter id="A" symbol="A" complement="T" name="Adenine" colour="CC0000"/>
      <letter id="C" symbol="C" complement="G" name="Cytosine" colour="0000CC"/>
      <letter id="G" symbol="G" complement="C" name="Guanine" colour="FFB300"/>
      <letter id="T" symbol="T" aliases="U" complement="A" name="Thymine" colour="008000"/>
      <letter id="N" symbol="N" aliases="X." equals="ACGT" name="Any base"/>
      <letter id="V" symbol="V" equals="ACG" name="Not T"/>
      <letter id="H" symbol="H" equals="ACT" name="Not G"/>
      <letter id="D" symbol="D" equals="AGT" name="Not C"/>
      <letter id="B" symbol="B" equals="CGT" name="Not A"/>
      <letter id="M" symbol="M" equals="AC" name="Amino"/>
      <letter id="R" symbol="R" equals="AG" name="Purine"/>
      <letter id="W" symbol="W" equals="AT" name="Weak"/>
      <letter id="S" symbol="S" equals="CG" name="Strong"/>
      <letter id="Y" symbol="Y" equals="CT" name="Pyrimidine"/>
      <letter id="K" symbol="K" equals="GT" name="Keto"/>
    </alphabet>
    <strands>both</strands>
    <background from="--query--" A="0.25" C="0.25" G="0.25" T="0.25"/>
    <host>n04</host>
    <when>Tue Dec  1 15:20:35 2020</when>
  </model>
  <query_dbs>
    <db source="result/x13154/x13154.meme" name="x13154" loaded="1" excluded="0" last_mod_date="Tue Dec  1 15:20:35 2020"/>
  </query_dbs>
  <target_dbs>
    <db source="../../../JASPAR2020.txt" name="JASPAR2020.txt" loaded="1011" excluded="0" last_mod_date="Fri Oct  9 07:50:57 2020"/>
  </target_dbs>
  <queries>
    <motif db="0" id="15010_2913_3.5674_1.2844" length="163" nsites="998">
      <pos A="0.261522" C="0.506988" G="0.119251" T="0.112238"/>
      <pos A="0.159168" C="0.404389" G="0.208212" T="0.22823"/>
      <pos A="0.246493" C="0.335662" G="0.249499" T="0.168345"/>
      <pos A="0.226228" C="0.412396" G="0.116129" T="0.245245"/>
      <pos A="0.396779" C="0.299594" G="0.126265" T="0.177362"/>
      <pos A="0.157324" C="0.442867" G="0.27655" T="0.123259"/>
      <pos A="0.293583" C="0.258516" G="0.174357" T="0.273545"/>
      <pos A="0.246493" C="0.206417" G="0.383755" T="0.163336"/>
      <pos A="0.196398" C="0.225453" G="0.364718" T="0.213431"/>
      <pos A="0.080258" C="0.257772" G="0.396174" T="0.265795"/>
      <pos A="0.0991141" C="0.210214" G="0.400385" T="0.290286"/>
      <pos A="0.090196" C="0.345681" G="0.432848" T="0.131275"/>
      <pos A="0.130273" C="0.459899" G="0.256512" T="0.153317"/>
      <pos A="0.312306" C="0.312306" G="0.259258" T="0.116129"/>
      <pos A="0.0972093" C="0.431846" G="0.363716" T="0.107228"/>
      <pos A="0.288573" C="0.210425" G="0.164338" T="0.336664"/>
      <pos A="0.126138" C="0.562532" G="0.190196" T="0.121134"/>
      <pos A="0.20241" C="0.322638" G="0.231465" T="0.243488"/>
      <pos A="0.250501" C="0.436855" G="0.236474" T="0.0761694"/>
      <pos A="0.271541" C="0.337666" G="0.159328" T="0.231465"/>
      <pos A="0.120133" C="0.333325" G="0.323316" T="0.223226"/>
      <pos A="0.177362" C="0.31863" G="0.200406" T="0.303602"/>
      <pos A="0.209213" C="0.285281" G="0.25025" T="0.255254"/>
      <pos A="0.060139" C="0.329651" G="0.336664" T="0.273545"/>
      <pos A="0.245491" C="0.256512" G="0.298592" T="0.199404"/>
      <pos A="0.133279" C="0.292581" G="0.483945" T="0.090196"/>
      <pos A="0.145301" C="0.219442" G="0.453888" T="0.18137"/>
      <pos A="0.0611409" C="0.233469" G="0.595155" T="0.110234"/>
      <pos A="0.185377" C="0.184376" G="0.326645" T="0.303602"/>
      <pos A="0.163499" C="0.109342" G="0.617817" T="0.109342"/>
      <pos A="0.137148" C="0.299294" G="0.209213" T="0.354344"/>
      <pos A="0.209633" C="0.17052" G="0.46738" T="0.152467"/>
      <pos A="0.0811789" C="0.5661" G="0.194395" T="0.158326"/>
      <pos A="0.377743" C="0.283564" G="0.267533" T="0.0711599"/>
      <pos A="0.0561314" C="0.750451" G="0.104223" T="0.0891941"/>
      <pos A="0.420825" C="0.29759" G="0.104223" T="0.177362"/>
      <pos A="0.253507" C="0.47092" G="0.146303" T="0.129271"/>
      <pos A="0.257514" C="0.234471" G="0.173355" T="0.334661"/>
      <pos A="0.238717" C="0.522541" G="0.191581" T="0.0471613"/>
      <pos A="0.388764" C="0.285567" G="0.0431067" T="0.282562"/>
      <pos A="0.173355" C="0.369727" G="0.236474" T="0.220444"/>
      <pos A="0.468916" C="0.262524" G="0.106226" T="0.162334"/>
      <pos A="0.234471" C="0.148307" G="0.332657" T="0.284566"/>
      <pos A="0.24449" C="0.0942036" G="0.510996" T="0.150311"/>
      <pos A="0.159487" C="0.0922928" G="0.440302" T="0.307918"/>
      <pos A="0.0891941" C="0.080177" G="0.770489" T="0.060139"/>
      <pos A="0.126265" C="0.0411029" G="0.691339" T="0.141294"/>
      <pos A="0.0871033" C="0.123136" G="0.611576" T="0.178185"/>
      <pos A="0.0871903" C="0.103221" G="0.540051" T="0.269537"/>
      <pos A="0.0531257" C="0.196398" G="0.597159" T="0.153317"/>
      <pos A="0.227457" C="0.298592" G="0.292581" T="0.18137"/>
      <pos A="0.286857" C="0.424256" G="0.218659" T="0.070229"/>
      <pos A="0.267533" C="0.458897" G="0.0891941" T="0.184376"/>
      <pos A="0.167343" C="0.668295" G="0.0831827" T="0.0811789"/>
      <pos A="0.0611409" C="0.645251" G="0.101217" T="0.192391"/>
      <pos A="0.183374" C="0.653267" G="0.104223" T="0.0591371"/>
      <pos A="0.313621" C="0.548066" G="0.0581352" T="0.080177"/>
      <pos A="0.34468" C="0.316626" G="0.0571333" T="0.28156"/>
      <pos A="0.431846" C="0.379747" G="0.0411029" T="0.147305"/>
      <pos A="0.303907" C="0.211639" G="0.0361294" T="0.448325"/>
      <pos A="0.15532" C="0.521015" G="0.24449" T="0.0791751"/>
      <pos A="0.708078" C="0.0652145" G="0.142438" T="0.0842696"/>
      <pos A="0.117247" C="0.205415" G="0.331655" T="0.345681"/>
      <pos A="0.365353" C="0.0420628" G="0.484461" T="0.108122"/>
      <pos A="0.0581352" C="0.0390991" G="0.656272" T="0.246493"/>
      <pos A="0.0511219" C="0.0230687" G="0.893723" T="0.0320858"/>
      <pos A="0.0160714" C="0.0311149" G="0.914677" T="0.0381352"/>
      <pos A="0.111236" C="0.0451105" G="0.494965" T="0.348687"/>
      <pos A="0.0391381" C="0.0451555" G="0.87757" T="0.0381352"/>
      <pos A="0.0360934" C="0.420825" G="0.0952055" T="0.447876"/>
      <pos A="0.377743" C="0.0641466" G="0.537045" T="0.0210649"/>
      <pos A="0.040101" C="0.854648" G="0.0571333" T="0.0481162"/>
      <pos A="0.46144" C="0.0861024" G="0.080097" T="0.37236"/>
      <pos A="0.0711599" C="0.85565" G="0.0340896" T="0.0390991"/>
      <pos A="0.05012" C="0.624211" G="0.0310839" T="0.294585"/>
      <pos A="0.117365" C="0.814386" G="0.0431497" T="0.0250975"/>
      <pos A="0.424256" C="0.432279" G="0.0622058" T="0.0812609"/>
      <pos A="0.372733" C="0.4078" G="0.05012" T="0.169347"/>
      <pos A="0.330653" C="0.222448" G="0.0250725" T="0.421827"/>
      <pos A="0.353343" C="0.448428" G="0.0380592" T="0.160169"/>
      <pos A="0.398783" C="0.291579" G="0.0911979" T="0.21844"/>
      <pos A="0.320956" C="0.200607" G="0.338005" T="0.140432"/>
      <pos A="0.310615" C="0.206417" G="0.258516" T="0.224452"/>
      <pos A="0.389766" C="0.0731637" G="0.382753" T="0.154319"/>
      <pos A="0.0881922" C="0.0831827" G="0.632227" T="0.196398"/>
      <pos A="0.161332" C="0.0591371" G="0.724401" T="0.0551295"/>
      <pos A="0.0681542" C="0.0581352" G="0.838618" T="0.0350915"/>
      <pos A="0.0541276" C="0.0360934" G="0.640242" T="0.269537"/>
      <pos A="0.0350915" C="0.123259" G="0.762474" T="0.0791751"/>
      <pos A="0.0772493" C="0.344023" G="0.223674" T="0.355054"/>
      <pos A="0.232234" C="0.154164" G="0.564533" T="0.0490691"/>
      <pos A="0.110345" C="0.705069" G="0.0421468" T="0.142438"/>
      <pos A="0.358706" C="0.185377" G="0.25551" T="0.200406"/>
      <pos A="0.0641466" C="0.787521" G="0.0741656" T="0.0741656"/>
      <pos A="0.217438" C="0.561091" G="0.0731637" T="0.148307"/>
      <pos A="0.0810979" C="0.78273" G="0.0830997" T="0.0530727"/>
      <pos A="0.439861" C="0.332657" G="0.117247" T="0.110234"/>
      <pos A="0.292288" C="0.454434" G="0.177184" T="0.0760934"/>
      <pos A="0.440863" C="0.141294" G="0.146303" T="0.271541"/>
      <pos A="0.172526" C="0.389154" G="0.366086" T="0.0722348"/>
      <pos A="0.332657" C="0.172353" G="0.210425" T="0.284566"/>
      <pos A="0.235708" C="0.19459" G="0.438296" T="0.131406"/>
      <pos A="0.335662" C="0.164338" G="0.291579" T="0.208421"/>
      <pos A="0.122257" C="0.170349" G="0.632227" T="0.0751675"/>
      <pos A="0.225227" C="0.380367" G="0.291287" T="0.103118"/>
      <pos A="0.194395" C="0.175358" G="0.452886" T="0.177362"/>
      <pos A="0.0792551" C="0.451334" G="0.425258" T="0.0441526"/>
      <pos A="0.159487" C="0.256769" G="0.297889" T="0.285854"/>
      <pos A="0.105225" C="0.382753" G="0.423831" T="0.0881922"/>
      <pos A="0.182372" C="0.334661" G="0.331655" T="0.151313"/>
      <pos A="0.151313" C="0.301598" G="0.441865" T="0.105225"/>
      <pos A="0.27227" C="0.338329" G="0.147157" T="0.242243"/>
      <pos A="0.143298" C="0.211427" G="0.436855" T="0.208421"/>
      <pos A="0.111236" C="0.457895" G="0.247495" T="0.183374"/>
      <pos A="0.187381" C="0.343678" G="0.316626" T="0.152315"/>
      <pos A="0.114242" C="0.503983" G="0.217438" T="0.164338"/>
      <pos A="0.262261" C="0.359348" G="0.319312" T="0.0590781"/>
      <pos A="0.200607" C="0.49847" G="0.171523" T="0.1294"/>
      <pos A="0.420825" C="0.104223" G="0.283564" T="0.191389"/>
      <pos A="0.120253" C="0.509994" G="0.292581" T="0.0771713"/>
      <pos A="0.315308" C="0.1942" G="0.137148" T="0.353343"/>
      <pos A="0.156322" C="0.396779" G="0.356702" T="0.090196"/>
      <pos A="0.22823" C="0.333325" G="0.241242" T="0.197202"/>
      <pos A="0.119251" C="0.320634" G="0.324642" T="0.235472"/>
      <pos A="0.279556" C="0.332657" G="0.196398" T="0.191389"/>
      <pos A="0.0832667" C="0.273819" G="0.387147" T="0.255766"/>
      <pos A="0.172353" C="0.556081" G="0.215434" T="0.0561314"/>
      <pos A="0.39177" C="0.216436" G="0.16033" T="0.231465"/>
      <pos A="0.0661504" C="0.497971" G="0.286569" T="0.149309"/>
      <pos A="0.408802" C="0.204414" G="0.16033" T="0.226455"/>
      <pos A="0.205415" C="0.284566" G="0.368725" T="0.141294"/>
      <pos A="0.233703" C="0.333994" G="0.197598" T="0.234706"/>
      <pos A="0.128397" C="0.212642" G="0.506494" T="0.152467"/>
      <pos A="0.197202" C="0.241242" G="0.323316" T="0.238239"/>
      <pos A="0.0851865" C="0.263526" G="0.432848" T="0.21844"/>
      <pos A="0.134281" C="0.36071" G="0.251503" T="0.253507"/>
      <pos A="0.285567" C="0.145301" G="0.415815" T="0.153317"/>
      <pos A="0.0911979" C="0.371731" G="0.204414" T="0.332657"/>
      <pos A="0.390768" C="0.153317" G="0.296588" T="0.159328"/>
      <pos A="0.120253" C="0.477933" G="0.290577" T="0.111236"/>
      <pos A="0.230694" C="0.354052" G="0.183558" T="0.231697"/>
      <pos A="0.185377" C="0.426836" G="0.298592" T="0.0891941"/>
      <pos A="0.150311" C="0.352695" G="0.238478" T="0.258516"/>
      <pos A="0.231233" C="0.278275" G="0.393379" T="0.0971123"/>
      <pos A="0.252252" C="0.309303" G="0.208212" T="0.230232"/>
      <pos A="0.258516" C="0.280558" G="0.224452" T="0.236474"/>
      <pos A="0.290577" C="0.493964" G="0.0942036" T="0.121255"/>
      <pos A="0.366721" C="0.201408" G="0.118249" T="0.313621"/>
      <pos A="0.176537" C="0.51552" G="0.17754" T="0.130403"/>
      <pos A="0.322315" C="0.389375" G="0.177184" T="0.111125"/>
      <pos A="0.137286" C="0.450882" G="0.18137" T="0.230463"/>
      <pos A="0.250501" C="0.337666" G="0.226455" T="0.185377"/>
      <pos A="0.29759" C="0.149309" G="0.451884" T="0.101217"/>
      <pos A="0.24449" C="0.204414" G="0.346683" T="0.204414"/>
      <pos A="0.1443" C="0.341674" G="0.32364" T="0.190387"/>
      <pos A="0.273545" C="0.288573" G="0.269537" T="0.168345"/>
      <pos A="0.219442" C="0.31863" G="0.320634" T="0.141294"/>
      <pos A="0.227457" C="0.425834" G="0.212429" T="0.134281"/>
      <pos A="0.371101" C="0.183558" G="0.272816" T="0.172526"/>
      <pos A="0.171351" C="0.439861" G="0.221446" T="0.167343"/>
      <pos A="0.29759" C="0.225453" G="0.275548" T="0.201408"/>
      <pos A="0.198402" C="0.438859" G="0.222448" T="0.140292"/>
      <pos A="0.195592" C="0.382133" G="0.225679" T="0.196595"/>
    </motif>
  </queries>
  <targets>
  </targets>
  <matches>
  </matches>
  <runtime cycles="1701115676" seconds="1701.116"/>
</tomtom>
